libvipster.dll
vipster.cp39-win_amd64.pyd
vipster-1.19.1.dist-info/LICENSE
vipster-1.19.1.dist-info/METADATA
vipster-1.19.1.dist-info/WHEEL
vipster-1.19.1.dist-info/top_level.txt
vipster-1.19.1.dist-info/RECORD
